aiman/__init__.py
aiman/client/__init__.py
aiman/client/_ai_man_client.py
aiman/core/__init__.py
aiman/core/classes.py
aiman/core/credentials.py
aiman/core/util.py
tests/__init__.py
tests/aiman/classes_test.py
tests/aiman/util_test.py
venv/bin/activate_this.py
aiman_client-1.0.21.dist-info/LICENSE
aiman_client-1.0.21.dist-info/METADATA
aiman_client-1.0.21.dist-info/WHEEL
aiman_client-1.0.21.dist-info/top_level.txt
aiman_client-1.0.21.dist-info/RECORD
