Metadata-Version: 2.2
Name: aiman-client
Version: 1.0.21
Summary: Client Library to communicate with AIMan-API
Author-email: brandcompete GmbH <info@brandcompete.com>, Thorsten Atzeni <thorsten.atzeni@brandcompete.com>, Dennis Hauser <dennis.hauser@brandcompete.com>
Project-URL: Homepage, https://www.brandcompete.com
Project-URL: Source, https://github.com/brandcompete/aiman-apiclient-python
Project-URL: AIMan-Login, https://aiman.brandcompete.com
Classifier: Development Status :: 4 - Beta
Classifier: Environment :: Console
Classifier: Intended Audience :: Science/Research
Classifier: License :: OSI Approved :: Apache Software License
Classifier: Natural Language :: English
Classifier: Operating System :: OS Independent
Classifier: Programming Language :: Python
Classifier: Programming Language :: Python :: 3
Classifier: Programming Language :: Python :: 3 :: Only
Classifier: Programming Language :: Python :: 3.8
Classifier: Programming Language :: Python :: 3.9
Classifier: Programming Language :: Python :: 3.10
Classifier: Programming Language :: Python :: 3.11
Classifier: Programming Language :: Python :: 3.12
Classifier: Topic :: Scientific/Engineering :: Artificial Intelligence
Requires-Python: >=3.8
License-File: LICENSE
Requires-Dist: pyjwt
Requires-Dist: requests
Requires-Dist: setuptools
Provides-Extra: dev
Requires-Dist: pylint; extra == "dev"
Requires-Dist: toml; extra == "dev"
Requires-Dist: yapf; extra == "dev"
Provides-Extra: test
Requires-Dist: pytest-cov; extra == "test"
